scottschreckengaust/__init__.py
scottschreckengaust/placeholder_package/__init__.py
scottschreckengaust_placeholder_package-0.0.0.dist-info/licenses/LICENSE
scottschreckengaust_placeholder_package-0.0.0.dist-info/licenses/NOTICE
scottschreckengaust_placeholder_package-0.0.0.dist-info/METADATA
scottschreckengaust_placeholder_package-0.0.0.dist-info/WHEEL
scottschreckengaust_placeholder_package-0.0.0.dist-info/top_level.txt
scottschreckengaust_placeholder_package-0.0.0.dist-info/RECORD
