Metadata-Version: 2.4
Name: scottschreckengaust.placeholder-package
Version: 0.0.0
Summary: Placeholder package - not operational
Author-email: AWS Labs <awslabs@amazon.com>
License: Apache-2.0
Project-URL: Homepage, https://github.com/scottschreckengaust/mcp
Project-URL: Repository, https://github.com/scottschreckengaust/mcp
Project-URL: Issues, https://github.com/scottschreckengaust/mcp/issues
Keywords: placeholder,reserved,awslabs
Classifier: Development Status :: 1 - Planning
Classifier: Intended Audience :: Developers
Classifier: License :: OSI Approved :: Apache Software License
Classifier: Programming Language :: Python :: 3
Classifier: Programming Language :: Python :: 3.10
Classifier: Programming Language :: Python :: 3.11
Classifier: Programming Language :: Python :: 3.12
Classifier: Programming Language :: Python :: 3.13
Requires-Python: >=3.10
License-File: LICENSE
License-File: NOTICE
Dynamic: license-file
